progresslight/__init__.py
progresslight/cli.py
progresslight/log.py
progresslight/progress.py
progresslight-0.1.0.dist-info/licenses/LICENSE
progresslight-0.1.0.dist-info/METADATA
progresslight-0.1.0.dist-info/WHEEL
progresslight-0.1.0.dist-info/entry_points.txt
progresslight-0.1.0.dist-info/top_level.txt
progresslight-0.1.0.dist-info/RECORD
