Metadata-Version: 2.4
Name: progresslight
Version: 0.1.0
Summary: Lightweight CLI progress and logging helpers.
Author: ProgressLight
License-Expression: MIT
Project-URL: Homepage, https://pypi.org/project/progresslight/
Classifier: Programming Language :: Python :: 3
Classifier: Environment :: Console
Requires-Python: >=3.8
License-File: LICENSE
Provides-Extra: dev
Requires-Dist: build>=1.2.1; extra == "dev"
Requires-Dist: twine>=6.1.0; extra == "dev"
Requires-Dist: wheel>=0.45.1; extra == "dev"
Dynamic: license-file
